scons_msvc_env/__init__.py
scons_msvc_env/implib_from_dll.py
scons_msvc_env/msvc_env.py
scons_msvc_env/msvc_tools.py
scons_msvc_env/roma.stub
scons_msvc_env-1.0.0.dist-info/licenses/LICENSE
scons_msvc_env-1.0.0.dist-info/METADATA
scons_msvc_env-1.0.0.dist-info/WHEEL
scons_msvc_env-1.0.0.dist-info/top_level.txt
scons_msvc_env-1.0.0.dist-info/RECORD
